[{"Work":"Concerto for 3 (or 2) Pianos and Orchestra no. 7 in F major, K. 242 “Lodron”: I. Allegro","Writers":"Wolfgang Amadeus Mozart (composer)","Artists":"Concentus Hungaricus, Mátyás Antal, Jenő Jandó, Dénes Várjon  Haydn Sinfonietta Wien, Manfred Huss, Ronald Brautigam, Алексей Любимов  Lithuanian Chamber Orchestra, Saulius Sondeckis, Tatiana Nikolayeva, Eliso Konstantinova Virsaladze, Nikolai Lugansky  English Chamber Orchestra, Murray Perahia, Radu Lupu  Lucas & Arthur Jussen, Academy of St Martin in the Fields, Sir Neville Marriner  English Chamber Orchestra, Sir Georg Solti, Daniel Barenboim, András Schiff  Orchestra da Camera di Padova e del Veneto, Bruno Giuranna, Duo Crommelynck  CBC Radio Orchestra, Mario Bernardi, Jon Kimura Parker, James Parker, Ian Parker  Katherine Jacobson Fleisher, Leon Fleisher, Stuttgarter Kammerorchester  Alfred Brendel, Imogen Cooper, Academy of St Martin in the Fields, Sir Neville Marriner  Sas Bunge, Ingrid Haebler, Ludwig Hoffmann, London Symphony Orchestra, Alceo Galliera  Alfredo Perl, Carmen Piazzini, Soloists of St. Petersburg, Michail Gantvarg  Malcolm Bilson, Robert Levin, Melvyn Tan, English Baroque Soloists, Sir John Eliot Gardiner  Silver-Garburg Piano Duo, Tasmanian Symphony Orchestra, Alexander Mickelthwate  Semyon Bychkov, Katia Labèque, Marielle Labèque, Berliner Philharmoniker  Capella Academica Wien, Eduard Melkus  Denise Dupont, Muriel Slatkine, Oswald Russel, Collegium Academicum de Genève, Robert Dunand  Vladimir Ashkenazy, Daniel Barenboim, Fou Ts'ong, English Chamber Orchestra  Alfredo Perl, Carmen Piazzini, Leningrad Soloists, Michael Gantvarg  Karl Engel, Till Engel, Leopold Hager, Mozarteum-Orchester Salzburg  Daniel Barenboim, András Schiff, Sir Georg Solti, English Chamber Orchestra  Zoltán Kocsis, Ránki Dezső, András Schiff, Nemzeti Filharmonikus Zenekar, János Ferencsik  Wolfgang Amadeus Mozart ;Viviana Sofronitzky,Musica Antiqua Collegium Varsovienese,Tadeusz Karolak, Linda Nicholson,Mario Aschauer  Christoph Eschenbach, Justus Frantz, Helmut Schmidt, London Philharmonic Orchestra  Martha Argerich, Paul Gulda, Rico Gulda, Orchestra della Svizzera italiana, Alexandre Rabinovitch-Barakovsky  Leonard Bernstein, Robert Fizdale, Arthur Gold, New York Philharmonic","ISWC":null,"Type":null,"Lyrics Languages":"zxx","Attributes":null,"Rating":null,"gid":"533ae15e-8d80-4d3c-8661-86e8762356e1"},{"Work":"Concerto for 3 (or 2) Pianos and Orchestra no. 7 in F major, K. 242 “Lodron”: II. Adagio","Writers":"Wolfgang Amadeus Mozart (composer)","Artists":"Concentus Hungaricus, Mátyás Antal, Jenő Jandó, Dénes Várjon  Haydn Sinfonietta Wien, Manfred Huss, Ronald Brautigam, Алексей Любимов  Lithuanian Chamber Orchestra, Saulius Sondeckis, Tatiana Nikolayeva, Eliso Konstantinova Virsaladze, Nikolai Lugansky  English Chamber Orchestra, Murray Perahia, Radu Lupu  Lucas & Arthur Jussen, Academy of St Martin in the Fields, Sir Neville Marriner  English Chamber Orchestra, Sir Georg Solti, Daniel Barenboim, András Schiff  Orchestra da Camera di Padova e del Veneto, Bruno Giuranna, Duo Crommelynck  CBC Radio Orchestra, Mario Bernardi, Jon Kimura Parker, James Parker, Ian Parker  Katherine Jacobson Fleisher, Leon Fleisher, Stuttgarter Kammerorchester  Alfred Brendel, Imogen Cooper, Academy of St Martin in the Fields, Sir Neville Marriner  Sas Bunge, Ingrid Haebler, Ludwig Hoffmann, London Symphony Orchestra, Alceo Galliera  Alfredo Perl, Carmen Piazzini, Soloists of St. Petersburg, Michail Gantvarg  Malcolm Bilson, Robert Levin, Melvyn Tan, English Baroque Soloists, Sir John Eliot Gardiner  Silver-Garburg Piano Duo, Tasmanian Symphony Orchestra, Alexander Mickelthwate  Semyon Bychkov, Katia Labèque, Marielle Labèque, Berliner Philharmoniker  Vladimir Ashkenazy, Daniel Barenboim, Fou Ts'ong, English Chamber Orchestra  Alfredo Perl, Carmen Piazzini, Leningrad Soloists, Michael Gantvarg  Karl Engel, Till Engel, Leopold Hager, Mozarteum-Orchester Salzburg  Daniel Barenboim, András Schiff, Sir Georg Solti, English Chamber Orchestra  Zoltán Kocsis, Ránki Dezső, András Schiff, Nemzeti Filharmonikus Zenekar, János Ferencsik  Wolfgang Amadeus Mozart ;Viviana Sofronitzky,Musica Antiqua Collegium Varsovienese,Tadeusz Karolak,Linda Nicholson,Mario Aschauer  Christoph Eschenbach, Justus Frantz, Helmut Schmidt, London Philharmonic Orchestra  Martha Argerich, Paul Gulda, Rico Gulda, Orchestra della Svizzera italiana, Alexandre Rabinovitch-Barakovsky  Leonard Bernstein, Robert Fizdale, Arthur Gold, New York Philharmonic","ISWC":null,"Type":null,"Lyrics Languages":"zxx","Attributes":null,"Rating":null,"gid":"533ae15e-8d80-4d3c-8661-86e8762356e1"},{"Work":"Concerto for 3 (or 2) Pianos and Orchestra no. 7 in F major, K. 242 “Lodron”: III. Rondo. Tempo di minuetto","Writers":"Wolfgang Amadeus Mozart (composer)","Artists":"Concentus Hungaricus, Mátyás Antal, Jenő Jandó, Dénes Várjon  Haydn Sinfonietta Wien, Manfred Huss, Ronald Brautigam, Алексей Любимов  Lithuanian Chamber Orchestra, Saulius Sondeckis, Tatiana Nikolayeva, Eliso Konstantinova Virsaladze, Nikolai Lugansky  English Chamber Orchestra, Murray Perahia, Radu Lupu  Lucas & Arthur Jussen, Academy of St Martin in the Fields, Sir Neville Marriner  English Chamber Orchestra, Sir Georg Solti, Daniel Barenboim, András Schiff  Orchestra da Camera di Padova e del Veneto, Bruno Giuranna, Duo Crommelynck  CBC Radio Orchestra, Mario Bernardi, Jon Kimura Parker, James Parker, Ian Parker  Katherine Jacobson Fleisher, Leon Fleisher, Stuttgarter Kammerorchester  Alfred Brendel, Imogen Cooper, Academy of St Martin in the Fields, Sir Neville Marriner  Sas Bunge, Ingrid Haebler, Ludwig Hoffmann, London Symphony Orchestra, Alceo Galliera  Alfredo Perl, Carmen Piazzini, Soloists of St. Petersburg, Michail Gantvarg  Malcolm Bilson, Robert Levin, Melvyn Tan, English Baroque Soloists, Sir John Eliot Gardiner  Silver-Garburg Piano Duo, Tasmanian Symphony Orchestra, Alexander Mickelthwate  Semyon Bychkov, Katia Labèque, Marielle Labèque, Berliner Philharmoniker  Vladimir Ashkenazy, Daniel Barenboim, Fou Ts'ong, English Chamber Orchestra  Alfredo Perl, Carmen Piazzini, Leningrad Soloists, Michael Gantvarg  Karl Engel, Till Engel, Leopold Hager, Mozarteum-Orchester Salzburg  Daniel Barenboim, András Schiff, Sir Georg Solti, English Chamber Orchestra  Zoltán Kocsis, Ránki Dezső, András Schiff, Nemzeti Filharmonikus Zenekar, János Ferencsik  Wolfgang Amadeus Mozart ;Viviana Sofronitzky,Musica Antiqua Collegium Varsovienese,Tadeusz Karolak,Linda Nicholson,Mario Aschauer  Christoph Eschenbach, Justus Frantz, Helmut Schmidt, London Philharmonic Orchestra  Martha Argerich, Paul Gulda, Rico Gulda, Orchestra della Svizzera italiana, Alexandre Rabinovitch-Barakovsky  Leonard Bernstein, Robert Fizdale, Arthur Gold, New York Philharmonic","ISWC":null,"Type":null,"Lyrics Languages":"zxx","Attributes":null,"Rating":null,"gid":"533ae15e-8d80-4d3c-8661-86e8762356e1"}]