[{"Work":"Alibi II","Writers":"Eric Douglas Porter (composer)","Artists":"Afrikan Sciences","ISWC":"T-916.176.173-5","Type":"Song","Lyrics Languages":null,"Attributes":null,"Rating":null,"gid":"76adbe46-d983-46d5-87a1-c62818543882"},{"Work":"Circuitous","Writers":"Eric Douglas Porter (composer)","Artists":"Afrikan Sciences","ISWC":"T-916.175.786-4","Type":"Song","Lyrics Languages":null,"Attributes":null,"Rating":null,"gid":"76adbe46-d983-46d5-87a1-c62818543882"},{"Work":"DBC","Writers":"Eric Douglas Porter (composer)","Artists":"Afrikan Sciences","ISWC":"T-916.176.174-6","Type":"Song","Lyrics Languages":null,"Attributes":null,"Rating":null,"gid":"76adbe46-d983-46d5-87a1-c62818543882"},{"Work":"Evolved in Twists","Writers":"Eric Douglas Porter (composer)","Artists":"Afrikan Sciences","ISWC":"T-916.175.905-3","Type":"Song","Lyrics Languages":null,"Attributes":null,"Rating":null,"gid":"76adbe46-d983-46d5-87a1-c62818543882"},{"Work":"Feel","Writers":"Eric Douglas Porter (composer)","Artists":"Afrikan Sciences","ISWC":"T-916.176.050-5","Type":"Song","Lyrics Languages":null,"Attributes":null,"Rating":null,"gid":"76adbe46-d983-46d5-87a1-c62818543882"},{"Work":"Group Home Reality","Writers":"Eric Douglas Porter (composer)","Artists":"Afrikan Sciences","ISWC":"T-916.176.171-3","Type":"Song","Lyrics Languages":null,"Attributes":null,"Rating":null,"gid":"76adbe46-d983-46d5-87a1-c62818543882"},{"Work":"I'm Asking You KB","Writers":"Eric Douglas Porter (composer)","Artists":"Afrikan Sciences","ISWC":"T-916.176.318-4","Type":"Song","Lyrics Languages":null,"Attributes":null,"Rating":null,"gid":"76adbe46-d983-46d5-87a1-c62818543882"},{"Work":"Kae","Writers":"Eric Douglas Porter (composer)","Artists":"Afrikan Sciences","ISWC":"T-916.175.906-4","Type":"Song","Lyrics Languages":null,"Attributes":null,"Rating":null,"gid":"76adbe46-d983-46d5-87a1-c62818543882"},{"Work":"Reddin Off","Writers":"Eric Douglas Porter (composer)","Artists":"Afrikan Sciences","ISWC":"T-916.175.789-7","Type":"Song","Lyrics Languages":null,"Attributes":null,"Rating":null,"gid":"76adbe46-d983-46d5-87a1-c62818543882"},{"Work":"Swash","Writers":"Eric Douglas Porter (composer)","Artists":"Afrikan Sciences","ISWC":"T-916.176.051-6","Type":"Song","Lyrics Languages":null,"Attributes":null,"Rating":null,"gid":"76adbe46-d983-46d5-87a1-c62818543882"},{"Work":"Tell Me Who Like That","Writers":"Eric Douglas Porter (composer)","Artists":"Afrikan Sciences","ISWC":"T-916.176.319-5","Type":"Song","Lyrics Languages":null,"Attributes":null,"Rating":null,"gid":"76adbe46-d983-46d5-87a1-c62818543882"},{"Work":"The Image","Writers":"Eric Douglas Porter (composer)","Artists":"Afrikan Sciences","ISWC":"T-916.176.054-9","Type":"Song","Lyrics Languages":null,"Attributes":null,"Rating":null,"gid":"76adbe46-d983-46d5-87a1-c62818543882"},{"Work":"Transient Authority","Writers":"Eric Douglas Porter (composer)","Artists":"Afrikan Sciences","ISWC":"T-916.175.904-2","Type":"Song","Lyrics Languages":null,"Attributes":null,"Rating":null,"gid":"76adbe46-d983-46d5-87a1-c62818543882"},{"Work":"Two in the Chamber","Writers":"Eric Douglas Porter (composer)","Artists":"Afrikan Sciences","ISWC":"T-916.175.787-5","Type":"Song","Lyrics Languages":null,"Attributes":null,"Rating":null,"gid":"76adbe46-d983-46d5-87a1-c62818543882"}]