[{"Work":"Aha Ke Ranga","Writers":"Ravindra Jain (composer)  Bhabesh Gupta (lyricist)","Artists":"Shipra Basu","ISWC":null,"Type":"Song","Lyrics Languages":"ben","Attributes":null,"Rating":null,"gid":"879301d6-f9ab-45c3-b5f3-ca7c2f500a5e"},{"Work":"Aha Mon Kamon Kare","Writers":"Himanshu Biswas (composer)  Lakshmikanta Roy (lyricist)","Artists":"Shipra Basu","ISWC":null,"Type":"Song","Lyrics Languages":"ben","Attributes":null,"Rating":null,"gid":"879301d6-f9ab-45c3-b5f3-ca7c2f500a5e"},{"Work":"Amar Badol Din","Writers":"Ravindra Jain (composer)  Bhabesh Gupta (lyricist)","Artists":"Shipra Basu","ISWC":null,"Type":"Song","Lyrics Languages":"ben","Attributes":null,"Rating":null,"gid":"879301d6-f9ab-45c3-b5f3-ca7c2f500a5e"},{"Work":"Amar Kabaar Maran","Writers":"Hemanta Mukherjee (composer)  Pulak Banerjee (lyricist)","Artists":"Shipra Basu","ISWC":null,"Type":"Song","Lyrics Languages":"ben","Attributes":null,"Rating":null,"gid":"879301d6-f9ab-45c3-b5f3-ca7c2f500a5e"},{"Work":"Amar Sada Rang","Writers":"Gauriprasanna Majumdar (lyricist)  Nachiketa Ghosh (composer)","Artists":"Shipra Basu","ISWC":null,"Type":"Song","Lyrics Languages":"ben","Attributes":null,"Rating":null,"gid":"879301d6-f9ab-45c3-b5f3-ca7c2f500a5e"},{"Work":"Ami Gadua Dhulite","Writers":"Himanshu Biswas (composer)  Shanti Bhattacharya (lyricist)","Artists":"Shipra Basu","ISWC":null,"Type":"Song","Lyrics Languages":"ben","Attributes":null,"Rating":null,"gid":"879301d6-f9ab-45c3-b5f3-ca7c2f500a5e"},{"Work":"Ami Shunechi Tar","Writers":"Hemanta Mukherjee (composer)  Ajay Bhattacharyya (lyricist)","Artists":"Shipra Basu","ISWC":null,"Type":"Song","Lyrics Languages":"ben","Attributes":null,"Rating":null,"gid":"879301d6-f9ab-45c3-b5f3-ca7c2f500a5e"},{"Work":"Bansuria Jane Go","Writers":"Sunil Baran (lyricist)  Sukumar Mitra (composer)","Artists":"Shipra Basu","ISWC":null,"Type":"Song","Lyrics Languages":"ben","Attributes":null,"Rating":null,"gid":"879301d6-f9ab-45c3-b5f3-ca7c2f500a5e"},{"Work":"Bhalobeshe Byatha","Writers":"Pranab Roy (lyricist)  Robin Chattopadhyay (composer)","Artists":"Shipra Basu","ISWC":null,"Type":"Song","Lyrics Languages":"ben","Attributes":null,"Rating":null,"gid":"879301d6-f9ab-45c3-b5f3-ca7c2f500a5e"},{"Work":"Byatha Kichu Chhilo Na","Writers":"Anupam Ghatak (composer)  Shanti Bhattacharya (lyricist)","Artists":"Shipra Basu","ISWC":null,"Type":"Song","Lyrics Languages":"ben","Attributes":null,"Rating":null,"gid":"879301d6-f9ab-45c3-b5f3-ca7c2f500a5e"},{"Work":"E Bhanga Basanta Belay","Writers":"Gauriprasanna Majumdar (lyricist)  Nachiketa Ghosh (composer)","Artists":"Shipra Basu","ISWC":null,"Type":"Song","Lyrics Languages":"ben","Attributes":null,"Rating":null,"gid":"879301d6-f9ab-45c3-b5f3-ca7c2f500a5e"},{"Work":"Ei Mon Okaran","Writers":"Sunil Baran (lyricist)  Nikhil Chatterjee (composer)","Artists":"Shipra Basu","ISWC":null,"Type":"Song","Lyrics Languages":"ben","Attributes":null,"Rating":null,"gid":"879301d6-f9ab-45c3-b5f3-ca7c2f500a5e"},{"Work":"Ghum Aasena","Writers":"Amalendu Bikash Kar Chowdhury (lyricist, composer)","Artists":"Shipra Basu","ISWC":null,"Type":"Song","Lyrics Languages":"ben","Attributes":null,"Rating":null,"gid":"879301d6-f9ab-45c3-b5f3-ca7c2f500a5e"},{"Work":"Jonaki Chayna","Writers":"Sunil Baran (lyricist)  Sukumar Mitra (composer)","Artists":"Shipra Basu","ISWC":null,"Type":"Song","Lyrics Languages":"ben","Attributes":null,"Rating":null,"gid":"879301d6-f9ab-45c3-b5f3-ca7c2f500a5e"},{"Work":"Kache Aasar Moto","Writers":"Hemanta Mukherjee (composer)  Pulak Banerjee (lyricist)","Artists":"Shipra Basu","ISWC":null,"Type":"Song","Lyrics Languages":"ben","Attributes":null,"Rating":null,"gid":"879301d6-f9ab-45c3-b5f3-ca7c2f500a5e"},{"Work":"Moner Duar Khule Ke","Writers":"Pranab Roy (lyricist)  Robin Chattopadhyay (composer)","Artists":"Shipra Basu","ISWC":null,"Type":"Song","Lyrics Languages":"ben","Attributes":null,"Rating":null,"gid":"879301d6-f9ab-45c3-b5f3-ca7c2f500a5e"},{"Work":"O Banshi Jane","Writers":"Sunil Baran (lyricist)  Nikhil Chatterjee (composer)","Artists":"Shipra Basu","ISWC":null,"Type":"Song","Lyrics Languages":"ben","Attributes":null,"Rating":null,"gid":"879301d6-f9ab-45c3-b5f3-ca7c2f500a5e"},{"Work":"Ogo Hridoy Raton","Writers":"Hemanta Mukherjee (composer)  Chitta Ranjan Das (lyricist)","Artists":"Shipra Basu","ISWC":null,"Type":"Song","Lyrics Languages":"ben","Attributes":null,"Rating":null,"gid":"879301d6-f9ab-45c3-b5f3-ca7c2f500a5e"},{"Work":"Phooler Byatha","Writers":"Ajoy Chakrabarty (composer)  Amar Shankar Bhattacharya (lyricist)","Artists":"Shipra Basu","ISWC":null,"Type":"Song","Lyrics Languages":"ben","Attributes":null,"Rating":null,"gid":"879301d6-f9ab-45c3-b5f3-ca7c2f500a5e"},{"Work":"Shono Katha","Writers":"Gauriprasanna Majumdar (writer)  Anupam Ghatak (composer)","Artists":"Shipra Basu","ISWC":null,"Type":"Song","Lyrics Languages":"ben","Attributes":null,"Rating":null,"gid":"879301d6-f9ab-45c3-b5f3-ca7c2f500a5e"}]