[{"Work":"Atoll","Writers":"Christopher Leary (composer)  David Sheppard (composer)","Artists":"Snow Palms","ISWC":null,"Type":null,"Lyrics Languages":null,"Attributes":null,"Rating":null,"gid":"a1426c9f-2c9d-43a7-85ae-67ab9705e3cb"},{"Work":"Blue Yonder","Writers":"Christopher Leary (composer)  David Sheppard (composer)","Artists":"Snow Palms","ISWC":null,"Type":null,"Lyrics Languages":null,"Attributes":null,"Rating":null,"gid":"a1426c9f-2c9d-43a7-85ae-67ab9705e3cb"},{"Work":"Delta Switching","Writers":"Christopher Leary (composer)  David Sheppard (composer)","Artists":"Snow Palms","ISWC":null,"Type":null,"Lyrics Languages":null,"Attributes":null,"Rating":null,"gid":"a1426c9f-2c9d-43a7-85ae-67ab9705e3cb"},{"Work":"In Camera","Writers":"David Sheppard (composer)","Artists":"Snow Palms","ISWC":null,"Type":null,"Lyrics Languages":null,"Attributes":null,"Rating":null,"gid":"a1426c9f-2c9d-43a7-85ae-67ab9705e3cb"},{"Work":"Index of Rivers","Writers":"David Sheppard (composer)","Artists":"Snow Palms","ISWC":null,"Type":null,"Lyrics Languages":null,"Attributes":null,"Rating":null,"gid":"a1426c9f-2c9d-43a7-85ae-67ab9705e3cb"},{"Work":"Light Museum","Writers":"David Sheppard (composer)","Artists":"Snow Palms","ISWC":null,"Type":null,"Lyrics Languages":null,"Attributes":null,"Rating":null,"gid":"a1426c9f-2c9d-43a7-85ae-67ab9705e3cb"},{"Work":"Motion Capture","Writers":"Christopher Leary (composer)  David Sheppard (composer)","Artists":"Snow Palms","ISWC":null,"Type":null,"Lyrics Languages":null,"Attributes":null,"Rating":null,"gid":"a1426c9f-2c9d-43a7-85ae-67ab9705e3cb"},{"Work":"Parafin Flat","Writers":"David Sheppard (writer)  Ian Bickerton (writer)","Artists":"Balloon","ISWC":null,"Type":null,"Lyrics Languages":null,"Attributes":null,"Rating":null,"gid":"a1426c9f-2c9d-43a7-85ae-67ab9705e3cb"},{"Work":"Premonition","Writers":"David Sheppard (composer)","Artists":"Snow Palms","ISWC":null,"Type":null,"Lyrics Languages":null,"Attributes":null,"Rating":null,"gid":"a1426c9f-2c9d-43a7-85ae-67ab9705e3cb"},{"Work":"Silence: John, Yvar and Tim","Writers":"Stephen Montague (composer)","Artists":"The Smith Quartet, Philip Mead, David Sheppard","ISWC":null,"Type":null,"Lyrics Languages":null,"Attributes":null,"Rating":null,"gid":"a1426c9f-2c9d-43a7-85ae-67ab9705e3cb"},{"Work":"Snow Light","Writers":"Christopher Leary (composer)  David Sheppard (composer)","Artists":"Snow Palms","ISWC":null,"Type":null,"Lyrics Languages":null,"Attributes":null,"Rating":null,"gid":"a1426c9f-2c9d-43a7-85ae-67ab9705e3cb"},{"Work":"Swimming Figures","Writers":"Christopher Leary (composer)  David Sheppard (composer)","Artists":"Snow Palms","ISWC":null,"Type":null,"Lyrics Languages":null,"Attributes":null,"Rating":null,"gid":"a1426c9f-2c9d-43a7-85ae-67ab9705e3cb"},{"Work":"Theme From Cardinal Menthol","Writers":"David Sheppard (composer)  Keiron Phelan (composer)","Artists":"Keiron Phelan & David Sheppard","ISWC":"T-011.546.048-4","Type":null,"Lyrics Languages":null,"Attributes":null,"Rating":null,"gid":"a1426c9f-2c9d-43a7-85ae-67ab9705e3cb"},{"Work":"White Sea","Writers":"Christopher Leary (composer)  David Sheppard (composer)","Artists":"Snow Palms","ISWC":null,"Type":null,"Lyrics Languages":null,"Attributes":null,"Rating":null,"gid":"a1426c9f-2c9d-43a7-85ae-67ab9705e3cb"}]