[{"Work":"BORDER LINE","Writers":"a2c (composer)  yuiko (lyricist)","Artists":"Primary","ISWC":null,"Type":null,"Lyrics Languages":null,"Attributes":null,"Rating":null,"gid":"caf7bdb8-7b7b-4804-826d-18d33e8ee9fe"},{"Work":"fuss fuzz","Writers":"a2c (composer)  米山玩具 (lyricist)","Artists":"黒崎真音","ISWC":"T-102.005.116-3","Type":"Song","Lyrics Languages":"jpn","Attributes":"172-3628-2 (JASRAC ID)","Rating":null,"gid":"caf7bdb8-7b7b-4804-826d-18d33e8ee9fe"},{"Work":"Guilty","Writers":"a2c (composer)  TERRA (lyricist)","Artists":"MintJam","ISWC":null,"Type":"Song","Lyrics Languages":"jpn","Attributes":null,"Rating":null,"gid":"caf7bdb8-7b7b-4804-826d-18d33e8ee9fe"},{"Work":"RESISTANCE (Yakou Senki Viner)","Writers":"a2c (composer)  TERRA (lyricist)","Artists":"MintJam×ViViX","ISWC":null,"Type":"Song","Lyrics Languages":"jpn","Attributes":null,"Rating":null,"gid":"caf7bdb8-7b7b-4804-826d-18d33e8ee9fe"},{"Work":"Return to Destiny","Writers":"a2c (composer)  akane (lyricist)","Artists":"黒崎真音","ISWC":"T-102.002.127-4","Type":"Song","Lyrics Languages":"jpn","Attributes":"701-0087-0 (JASRAC ID)","Rating":null,"gid":"caf7bdb8-7b7b-4804-826d-18d33e8ee9fe"},{"Work":"恋花火","Writers":"a2c (lyricist, composer)  中原杏 (lyricist)","Artists":"月島きらり starring 久住小春（モーニング娘。）","ISWC":"T-101.841.787-1","Type":"Song","Lyrics Languages":"jpn","Attributes":"135-9940-2 (JASRAC ID)","Rating":null,"gid":"caf7bdb8-7b7b-4804-826d-18d33e8ee9fe"}]