[{"Work":"決意 ‐父の手紙‐ (Ninja Gaiden, NES)","Writers":"山岸継司 (composer)  新田竜一 (composer)","Artists":"zyko  Keiji Yamagishi  Norrin_Radd  Vijay van der Weijden & Job Wijkamp  More Yamasan & B.B","ISWC":null,"Type":null,"Lyrics Languages":null,"Attributes":null,"Rating":null,"gid":"e502193e-5b16-4c70-baf9-9baf867b424b"},{"Work":"鎮魂歌（レクイエム） (Ninja Gaiden, NES)","Writers":"山岸継司 (composer)  新田竜一 (composer)","Artists":"Russell Cox  goat  Keiji Yamagishi  Vijay van der Weijden & Job Wijkamp  More Yamasan & B.B","ISWC":null,"Type":null,"Lyrics Languages":"zxx","Attributes":null,"Rating":null,"gid":"e502193e-5b16-4c70-baf9-9baf867b424b"},{"Work":"鮮烈のリュウ (Ninja Gaiden, NES)","Writers":"山岸継司 (composer)  新田竜一 (composer)","Artists":"Vurez  松前公高  Daniel Tidwell  Ryce Beetz  Vijay van der Weijden & Job Wijkamp  More Yamasan & B.B","ISWC":null,"Type":null,"Lyrics Languages":"zxx","Attributes":null,"Rating":null,"gid":"e502193e-5b16-4c70-baf9-9baf867b424b"}]