[
  {
    "Work": "Another Winter (Seiken Densetsu 3)",
    "Writers": "菊田裕樹 (composer)",
    "Artists": "菊田裕樹  Abadoss  Rozovian  Lix  The Amazing BrandO",
    "ISWC": null,
    "Type": null,
    "Lyrics Languages": "zxx",
    "Attributes": null,
    "Rating": null,
    "gid": "ff0b4e56-ad1b-4d25-8707-042fc099293b"
  },
  {
    "Work": "Antipyretic (Final Fantasy Tactics)",
    "Writers": "崎元仁 (composer)",
    "Artists": "崎元仁  Lix",
    "ISWC": null,
    "Type": "Song",
    "Lyrics Languages": "zxx",
    "Attributes": null,
    "Rating": null,
    "gid": "ff0b4e56-ad1b-4d25-8707-042fc099293b"
  },
  {
    "Work": "Battle #5",
    "Writers": "伊藤賢治 (composer)",
    "Artists": "伊藤賢治  HIR  Lix",
    "ISWC": null,
    "Type": null,
    "Lyrics Languages": null,
    "Attributes": null,
    "Rating": null,
    "gid": "ff0b4e56-ad1b-4d25-8707-042fc099293b"
  },
  {
    "Work": "BT \"ultimate\"",
    "Writers": "浜渦正志 (composer)",
    "Artists": "Lix  浜渦正志",
    "ISWC": null,
    "Type": null,
    "Lyrics Languages": null,
    "Attributes": null,
    "Rating": null,
    "gid": "ff0b4e56-ad1b-4d25-8707-042fc099293b"
  },
  {
    "Work": "Decision Bell (Seiken Densetsu 3)",
    "Writers": "菊田裕樹 (composer)",
    "Artists": "rebrained  菊田裕樹  Lix  shammy",
    "ISWC": null,
    "Type": null,
    "Lyrics Languages": "zxx",
    "Attributes": null,
    "Rating": null,
    "gid": "ff0b4e56-ad1b-4d25-8707-042fc099293b"
  },
  {
    "Work": "DG \"sadness\"",
    "Writers": "浜渦正志 (composer)",
    "Artists": "浜渦正志  Lix",
    "ISWC": null,
    "Type": null,
    "Lyrics Languages": null,
    "Attributes": null,
    "Rating": null,
    "gid": "ff0b4e56-ad1b-4d25-8707-042fc099293b"
  },
  {
    "Work": "DG \"sine\"",
    "Writers": "浜渦正志 (composer)",
    "Artists": "浜渦正志  Lix  大臣",
    "ISWC": null,
    "Type": null,
    "Lyrics Languages": null,
    "Attributes": null,
    "Rating": null,
    "gid": "ff0b4e56-ad1b-4d25-8707-042fc099293b"
  },
  {
    "Work": "Force Your Way (Final Fantasy Ⅷ)",
    "Writers": "植松伸夫 (composer)",
    "Artists": "植松伸夫  The Black Mages  Lix  牧歌電子  Mykah  Anti-Syne  Jun Muratani  Triforce Quartet  EXCELSIA  ししあ  Nightlock  Rich Douglas  TAM×Hikaru  Moabi  TAM + Hikaru  Frog & Cid  NES Romancer  シエナ・ウインド・オーケストラ  Chequer Chequer feat. ArtanusVG",
    "ISWC": null,
    "Type": null,
    "Lyrics Languages": "zxx",
    "Attributes": null,
    "Rating": null,
    "gid": "ff0b4e56-ad1b-4d25-8707-042fc099293b"
  },
  {
    "Work": "Geometric City (Raystorm)",
    "Writers": "河本圭代 (composer)",
    "Artists": "ZUNTATA  河本圭代  矢鴇つかさ  Lix  森正樹  SHIGE & MAKOTO",
    "ISWC": null,
    "Type": null,
    "Lyrics Languages": null,
    "Attributes": "066-5519-0 (JASRAC ID)",
    "Rating": null,
    "gid": "ff0b4e56-ad1b-4d25-8707-042fc099293b"
  },
  {
    "Work": "Harvest Dance",
    "Writers": "崎元仁 (composer)",
    "Artists": "崎元仁  Lix",
    "ISWC": null,
    "Type": "Song",
    "Lyrics Languages": "zxx",
    "Attributes": null,
    "Rating": null,
    "gid": "ff0b4e56-ad1b-4d25-8707-042fc099293b"
  },
  {
    "Work": "Innocent Water (Seiken Densetsu 3)",
    "Writers": "菊田裕樹 (composer)",
    "Artists": "Lix  菊田裕樹  Emunator & Ergosonic",
    "ISWC": null,
    "Type": null,
    "Lyrics Languages": "zxx",
    "Attributes": null,
    "Rating": null,
    "gid": "ff0b4e56-ad1b-4d25-8707-042fc099293b"
  },
  {
    "Work": "Last regrets",
    "Writers": "KEY (composer)  麻枝准 (lyricist)",
    "Artists": "彩菜  Lia  Alstroemeria Records  島みやえい子  HIMEKA  島宮えい子  Lix  天戸屋成  RINA",
    "ISWC": null,
    "Type": "Song",
    "Lyrics Languages": "jpn",
    "Attributes": null,
    "Rating": null,
    "gid": "ff0b4e56-ad1b-4d25-8707-042fc099293b"
  },
  {
    "Work": "Legend of MANA (Title Theme) (Legend of Mana)",
    "Writers": "下村陽子 (composer)",
    "Artists": "下村陽子  Lix  Delldongo",
    "ISWC": null,
    "Type": null,
    "Lyrics Languages": null,
    "Attributes": null,
    "Rating": null,
    "gid": "ff0b4e56-ad1b-4d25-8707-042fc099293b"
  },
  {
    "Work": "Legendary Wings (Thunder Force V, Stage 1)",
    "Writers": "九十九百太郎 (composer)",
    "Artists": "九十九百太郎  どぶウサギ  Lix  S.S.H.",
    "ISWC": null,
    "Type": null,
    "Lyrics Languages": null,
    "Attributes": null,
    "Rating": null,
    "gid": "ff0b4e56-ad1b-4d25-8707-042fc099293b"
  },
  {
    "Work": "Limitation",
    "Writers": "崎元仁 (composer)",
    "Artists": "崎元仁  Lix  Delldongo",
    "ISWC": null,
    "Type": "Song",
    "Lyrics Languages": "zxx",
    "Attributes": null,
    "Rating": null,
    "gid": "ff0b4e56-ad1b-4d25-8707-042fc099293b"
  },
  {
    "Work": "Stab the Sword of Justice",
    "Writers": "桜庭統 (composer)",
    "Artists": "桜庭統  Daniel Tidwell  Lix",
    "ISWC": null,
    "Type": null,
    "Lyrics Languages": null,
    "Attributes": null,
    "Rating": null,
    "gid": "ff0b4e56-ad1b-4d25-8707-042fc099293b"
  },
  {
    "Work": "The Extreme (Final Fantasy VIII)",
    "Writers": "植松伸夫 (composer)",
    "Artists": "植松伸夫  The Black Mages  KPLECRAFT  ARM  Nekofrog  SHΛDE  Skummel Maske  Lix  Knight of the Round  Lastair, SnappleMan & norg  Jun Muratani  mouse on the keys  EXCELSIA  ししあ  あず♪  TAM×Hikaru  TAM + Hikaru  AnimeVivi & Auronlu7912  Pontus Hultgren feat. Matheus Manente",
    "ISWC": null,
    "Type": null,
    "Lyrics Languages": "zxx",
    "Attributes": null,
    "Rating": null,
    "gid": "ff0b4e56-ad1b-4d25-8707-042fc099293b"
  },
  {
    "Work": "The Flame and the Arrow (Riza)",
    "Writers": "笹井隆司 (composer)",
    "Artists": "笹井隆司  Lix",
    "ISWC": null,
    "Type": null,
    "Lyrics Languages": null,
    "Attributes": null,
    "Rating": null,
    "gid": "ff0b4e56-ad1b-4d25-8707-042fc099293b"
  },
  {
    "Work": "The Man with the Machine Gun (Final Fantasy VIII)",
    "Writers": "植松伸夫 (composer)",
    "Artists": "植松伸夫  Nobuo Uematsu  The Black Mages  Lix  Jun Muratani  Jan Van Valburg  Beatdrop  KPLECRAFT  Hellion Sounds  Standby  Nekofrog  Mykah  JOYH-TV  Smooth McGroove  yue  EXCELSIA  くもロブスター  ししあ  TAM×Gin  TeraCMusic  Mr. Alek & Toxodentrail",
    "ISWC": null,
    "Type": "Song",
    "Lyrics Languages": "zxx",
    "Attributes": null,
    "Rating": null,
    "gid": "ff0b4e56-ad1b-4d25-8707-042fc099293b"
  },
  {
    "Work": "TO MAKE THE END OF BATTLE",
    "Writers": "Falcom Sound Team jdk (previous attribution)",
    "Artists": "Falcom Sound Team jdk  jdk BAND  Hellion Sounds  Lix  TOKIO DANCE BEAT BAND  Vic Viper",
    "ISWC": null,
    "Type": null,
    "Lyrics Languages": null,
    "Attributes": null,
    "Rating": null,
    "gid": "ff0b4e56-ad1b-4d25-8707-042fc099293b"
  },
  {
    "Work": "おてんば恋娘 (東方紅魔郷)",
    "Writers": "ZUN (composer)",
    "Artists": "TAMUSIC  愛新覚羅溥儀  CROW'SCLAW  koro  玖原イヅナ  ZUN  Demetori  IOSYS  羽鳥風画  鯛の小骨  あきやまうに  Azure & Sands  Dark PHOENiX  Fragile Online  Silver Forest  Liz Triangle  Sensitive Heart  白いしましまうさぎ  Nanasy  ハルアゲイン  Melodic Taste  Alstroemeria Records & Cradle  Lix  uno  Bach  りぎょ  Sakino  yohine  隣人(ZYTOKINE\/CYTOKINE)  GET IN THE RING  Tracy  RichaadEB  凛  青猫  霧島静久  Melodic Taste & Lu-na  なきゃむりゃ  +tek",
    "ISWC": null,
    "Type": null,
    "Lyrics Languages": "zxx",
    "Attributes": null,
    "Rating": null,
    "gid": "ff0b4e56-ad1b-4d25-8707-042fc099293b"
  },
  {
    "Work": "クリスタルタワー (Final Fantasy III)",
    "Writers": "植松伸夫 (composer)",
    "Artists": "植松伸夫  Lix  関戸剛 & 山中康央 feat.Remi  春風の並木道  preludio  EXCELSIA  TAM×Gin  Ferdk",
    "ISWC": null,
    "Type": null,
    "Lyrics Languages": "zxx",
    "Attributes": null,
    "Rating": null,
    "gid": "ff0b4e56-ad1b-4d25-8707-042fc099293b"
  },
  {
    "Work": "シルバード〜時を渡る翼〜 (“Epoch -Wings of Time-” from Chrono Trigger)",
    "Writers": "光田康典 (composer)",
    "Artists": "光田康典  Kirby's Dream Band  Dale North  Claado Shou  Vernian Process  Lix  The Blake Robinson Synthetic Orchestra  melody & Chris ~ Amaterasu  RF  EXCELSIA  Sean Schafianski  Careless Juja feat. \"Saxy\" Quaid Atkinson  Nostalvania & The OC Jazz Collective",
    "ISWC": null,
    "Type": "Song",
    "Lyrics Languages": "zxx",
    "Attributes": "034-3652-7 (JASRAC ID)",
    "Rating": null,
    "gid": "ff0b4e56-ad1b-4d25-8707-042fc099293b"
  },
  {
    "Work": "ティナのテーマ (Final Fantasy VI)",
    "Writers": "植松伸夫 (composer)",
    "Artists": "植松伸夫  Nobuo Uematsu  Ailsean  Jovette Rivera  SHO  Brandon Strader  Daniel Tidwell  Random Encounter  Jun Muratani  EXCELSIA  小林潔  RebeccaETripp  Shiryu  Jeremy Soule  Dale North  mp  SunnyVale  Alexander Prievert  Tim Sheehy  Darangen  The OneUps  Nicholai Duval  Trace Dragon XVI K  石元丈晴  Rexy  TAMUSIC  Vernian Process  Fishy  OA  Chad Seiter  CROW'SCLAW  TAM  halc  Benyamin Nuss  Select Start  Dangerous Mezashi Cat  Aaron Freed  Wizwars  Snow Productions  SHΛDE  Ante  SiJ  Lix  Gnilp Lasso  DragonAvenger & OA  203soundworks  Erock  The World is Square  AmIEviL  JV & djbrilliant  K-Murdock  TAM  DDRKirby(ISQ)  Derek Oren & Jeremy Robson  timaeus222  jaxx  Dagmar Krug  TheRedMage13  James Stuart  Delldongo  ZackParrish, Jesús Chic Acevedo & Pearl Pixel  春風の並木道  Triforce Quartet  Hi-KICK  似非  こっけ  清水嶺  Catherine Felze  Ton2  あず♪  くぼた牧之介  Dragonbard  TAM + 弦奏楽団  Zebes System  pingosimon  Ferdk  TeraCMusic  Jazz Paladin  Hollywood Symphony Orchestra & The Electric Sound Ensemble  Toxodentrail & GameLark  Mariachi Entertainment System  シエナ・ウインド・オーケストラ  Sab Irene  OceansAndrew  Bullicann, Team Friesen, John Stacy, TonalRumblePak & Hashel  Eiko Nichols  Kara Comparetto  TAM + ARUNA",
    "ISWC": null,
    "Type": "Song",
    "Lyrics Languages": "zxx",
    "Attributes": null,
    "Rating": null,
    "gid": "ff0b4e56-ad1b-4d25-8707-042fc099293b"
  },
  {
    "Work": "テクノdeチョコボ (Final Fantasy VI)",
    "Writers": "植松伸夫 (composer)",
    "Artists": "植松伸夫  Tepid  Joshua Morse  Lix  Yuzostupid  THE VOODOO BROTHERS  KeNji  YAMAGEN  Thibault Triat",
    "ISWC": null,
    "Type": null,
    "Lyrics Languages": "zxx",
    "Attributes": null,
    "Rating": null,
    "gid": "ff0b4e56-ad1b-4d25-8707-042fc099293b"
  },
  {
    "Work": "デザイアドライブ (東方神霊廟)",
    "Writers": "ZUN (composer)",
    "Artists": "ZUN  Shibayan Records  凛  魂音泉  REDALiCE  Lix  ハム  ZYTOKINE  ginkiha  梶迫迅八  着席無言",
    "ISWC": null,
    "Type": null,
    "Lyrics Languages": "zxx",
    "Attributes": null,
    "Rating": null,
    "gid": "ff0b4e56-ad1b-4d25-8707-042fc099293b"
  },
  {
    "Work": "バトル1",
    "Writers": "伊藤賢治 (composer)",
    "Artists": "伊藤賢治  Lix  椎名治美 & なみへい",
    "ISWC": null,
    "Type": "Song",
    "Lyrics Languages": "zxx",
    "Attributes": null,
    "Rating": null,
    "gid": "ff0b4e56-ad1b-4d25-8707-042fc099293b"
  },
  {
    "Work": "バトル１ (Final Fantasy V)",
    "Writers": "植松伸夫 (composer)",
    "Artists": "植松伸夫  石元丈晴  Lix  春風の並木道  EXCELSIA  MrSolidSnake745's Floppy Drive Orchestra  Sixto Sounds feat. Jeff Ball",
    "ISWC": null,
    "Type": "Song",
    "Lyrics Languages": "zxx",
    "Attributes": null,
    "Rating": null,
    "gid": "ff0b4e56-ad1b-4d25-8707-042fc099293b"
  },
  {
    "Work": "バトル２ (Final Fantasy V)",
    "Writers": "植松伸夫 (composer)",
    "Artists": "植松伸夫  おのっち  Lix  Knight of the Round  いわま ひろゆき  Jun Muratani  EXCELSIA  Ton2  TAM×ときまどうし  Discord Registers",
    "ISWC": null,
    "Type": null,
    "Lyrics Languages": "zxx",
    "Attributes": null,
    "Rating": null,
    "gid": "ff0b4e56-ad1b-4d25-8707-042fc099293b"
  },
  {
    "Work": "ビッグブリッヂの死闘 (Final Fantasy V)",
    "Writers": "植松伸夫 (composer)",
    "Artists": "植松伸夫  The Black Mages  石元丈晴  Hellion Sounds  SHO  Nobuo Uematsu  Jun Muratani  Ton2  Chris Tilton  東京フィルハーモニー交響楽団  Josh Barron  Shnabubula  TAMUSIC  norg  LuIzA  Piano Squall  CROW'SCLAW  Pocomoxo  The Red Wings  pu_freak  →Pia-no-jaC←  SHΛDE  栗コーダーカルテット  Lix  WDR Rundfunkorchester Köln & WDR Rundfunk Chor Köln  真中あきひと  Random Encounter  YDK  JOYH-TV  Godspeed  SQUARE ENIX MUSIC  関口祐二  yue  TheRedMage13  AOiRO_Manbow  いわま ひろゆき  preludio  Ryoji&Beta  EXCELSIA  とのづき  二矢  ししあ  LUNA  WATA☆MIN  あず♪  the forget-me-not  Dragonbard  TAM×A-dash×なみへい  TAM + A-dash + なみへい  南澤大介  Ferdk  Frog & Cid  KeNji  Triforcefilms Sound & GameLark  Hashel05 & Lord Bif Music",
    "ISWC": null,
    "Type": "Soundtrack",
    "Lyrics Languages": "zxx",
    "Attributes": "023-6737-8 (JASRAC ID)",
    "Rating": null,
    "gid": "ff0b4e56-ad1b-4d25-8707-042fc099293b"
  },
  {
    "Work": "ファイナルファンタジーIV・メインテーマ (Final Fantasy IV)",
    "Writers": "植松伸夫 (composer)",
    "Artists": "植松伸夫  Nutritious  Lix  Stephen Kennedy  FFmusic Dj  Mustin  Isopropyl  石元丈晴  John Revoredo  ARM  audio fidelity  Phat Stylee  The Blake Robinson Synthetic Orchestra  Midioker  tasuku  関口祐二  TheRedMage13  いわま ひろゆき  Jun Muratani  EXCELSIA  真井田ケイ  Sean Schafianski  くぼた牧之介  Hashel05  ATP",
    "ISWC": null,
    "Type": "Song",
    "Lyrics Languages": "zxx",
    "Attributes": null,
    "Rating": null,
    "gid": "ff0b4e56-ad1b-4d25-8707-042fc099293b"
  },
  {
    "Work": "フォールオブフォール ～ 秋めく滝 (東方風神録)",
    "Writers": "ZUN (composer)",
    "Artists": "TAM  凛  ZUN  TAMUSIC  IOSYS  REDALiCE  Azure & Sands  SWING HOLIC  Dark PHOENiX  こなぐすり  Silver Forest  オーライフジャパン  白いしましまうさぎ  光収容  幻想郷グリークラブ  Free-Logic  MAIKAZE  38BEETS  まらしぃ  Lix  Bach  Maurits\"禅\"Cornelis  岸田教団&THE明星ロケッツ  石山  REDALiCE feat.野宮あゆみ  REDALiCE feat.佳織みちる",
    "ISWC": null,
    "Type": null,
    "Lyrics Languages": "zxx",
    "Attributes": null,
    "Rating": null,
    "gid": "ff0b4e56-ad1b-4d25-8707-042fc099293b"
  },
  {
    "Work": "ボーダーオブライフ (東方妖々夢)",
    "Writers": "ZUN (composer)",
    "Artists": "ZUN  WAVE  青汁  絃奏水琴樂章  Sepher Project  Silver Forest  むらおあつし  まらしぃ  Round Table Minoshima  Bizen  Lix  Maurits\"禅\"Cornelis  HertzDevil  凛  紅薙たびびと  魂音泉  漂流いかだ(KOR)",
    "ISWC": null,
    "Type": null,
    "Lyrics Languages": "zxx",
    "Attributes": null,
    "Rating": null,
    "gid": "ff0b4e56-ad1b-4d25-8707-042fc099293b"
  },
  {
    "Work": "ラストバトル",
    "Writers": "伊藤賢治 (composer)",
    "Artists": "伊藤賢治  九十九百太郎  Lix",
    "ISWC": null,
    "Type": "Song",
    "Lyrics Languages": "zxx",
    "Attributes": null,
    "Rating": null,
    "gid": "ff0b4e56-ad1b-4d25-8707-042fc099293b"
  },
  {
    "Work": "ラストバトル (“The Final Battle” from Chrono Trigger)",
    "Writers": "光田康典 (composer)",
    "Artists": "光田康典  ABG  RoeTaKa  PLBenjaminZ  RaverRose  DrumUltimA  Lashmush  ellywu2 & pixietricks  Lix  The Blake Robinson Synthetic Orchestra  Jun Muratani  ししあ  The Greatest Bits  Matthew S. Harrison  Malcolm Robinson",
    "ISWC": null,
    "Type": null,
    "Lyrics Languages": "zxx",
    "Attributes": "034-3652-7 (JASRAC ID)",
    "Rating": null,
    "gid": "ff0b4e56-ad1b-4d25-8707-042fc099293b"
  },
  {
    "Work": "人形裁判 ～ 人の形弄びし少女 (東方妖々夢)",
    "Writers": "ZUN (composer)",
    "Artists": "愛新覚羅溥儀  TAMUSIC  絃奏水琴樂章  ZUN  WAVE  IOSYS  REDALiCE  CROW'SCLAW  EastNewSound  UI-70  Monochrome  Azure & Sands  C-CLAYS  U2  Scinicade  石鹸屋  Yellow Zebra  川瀬  SYNC.ART'S  まらしぃ  Sound 01  Pizuya's Cell × MyonMyon  koutaq  Lix  uno  Godspeed  龍5150  HertzDevil  発熱巫女〜ず  hoshi  凛  +tek  Baguettes Ensemble",
    "ISWC": null,
    "Type": null,
    "Lyrics Languages": "zxx",
    "Attributes": null,
    "Rating": null,
    "gid": "ff0b4e56-ad1b-4d25-8707-042fc099293b"
  },
  {
    "Work": "仲間を求めて (Final Fantasy VI)",
    "Writers": "植松伸夫 (composer)",
    "Artists": "植松伸夫  Lix  Jenova Project  koro  Jun Muratani  The Returners  大臣  Orkybash  JJT  NoppZ  Random Encounter  えくす  Joshua Morse feat. Jeff Ball, Laura Intravia  So many tears  Krank  関口祐二  yue  Sebastian Belleudy  Delldongo  いわま ひろゆき  春風の並木道  Hi-KICK  EXCELSIA  真井田ケイ  ししあ  LUNA  in  TAM×大臣×Isami  氏堂悠  ゆみつか  TAM + A-dash  Crystal Dennis  Eiko Nichols  ChequerChequer & Ferdk  Kara Comparetto  Pontus Hultgren",
    "ISWC": null,
    "Type": "Soundtrack",
    "Lyrics Languages": "zxx",
    "Attributes": "028-8681-2 (JASRAC ID)",
    "Rating": null,
    "gid": "ff0b4e56-ad1b-4d25-8707-042fc099293b"
  },
  {
    "Work": "信仰は儚き人間の為に (東方風神録)",
    "Writers": "ZUN (composer)",
    "Artists": "TAMUSIC  IOSYS  発熱巫女〜ず  凛  ZUN  UI-70  Demetori  あきやまうに  CROW'SCLAW  Azure & Sands  TAM  IRON ATTACK!  MyonMyon  SWING HOLIC  三澤秋  天音  石鹸屋  eS=S  Silver Forest  オーライフジャパン  SHO  UtAGe  幻想郷グリークラブ  時雨月横丁  ELEMENTAS  TatshMusicCircle  efs  Melodic Taste  いえろ～ぜぶら×電開製作所  Lix  Bach  うんちく商事  yohine  GET IN THE RING  西方風来  馬島昇  Edelritter  Remember memories.",
    "ISWC": null,
    "Type": null,
    "Lyrics Languages": "zxx",
    "Attributes": null,
    "Rating": null,
    "gid": "ff0b4e56-ad1b-4d25-8707-042fc099293b"
  },
  {
    "Work": "千年幻想郷 ～ History of the Moon (東方永夜抄)",
    "Writers": "ZUN (composer)",
    "Artists": "TAMUSIC  WAVE  愛新覚羅溥儀  ZUN  IOSYS  絃奏水琴樂章  Like a rabbit  Lix  凛  Masayoshi Minoshima  Tatsh  UI-70  Diverse System  Azure & Sands  SOUND HOLIC  C-CLAYS  MyonMyon  Sepher Project  夜皇禰実  SWING HOLIC  Alstroemeria Records  三澤秋  Scinicade  Dark PHOENiX  =NeutraL=  こなぐすり  Silver Forest  Liz Triangle  葉月ゆら  Sensitive Heart  Kraster  白いしましまうさぎ  UtAGe  Alice Music  38BEETS  まらしぃ  Sound 01  Cororo  Melodic Taste  いえろ～ぜぶら×電開製作所  Bizen  koro  void  Babbe  nekodex  交響アクティブNEETs  +tek  Baguettes Ensemble  着席無言",
    "ISWC": null,
    "Type": null,
    "Lyrics Languages": "zxx",
    "Attributes": null,
    "Rating": null,
    "gid": "ff0b4e56-ad1b-4d25-8707-042fc099293b"
  },
  {
    "Work": "四魔貴族バトル2",
    "Writers": "伊藤賢治 (composer)",
    "Artists": "伊藤賢治  HIR  Lix",
    "ISWC": null,
    "Type": "Song",
    "Lyrics Languages": "zxx",
    "Attributes": null,
    "Rating": null,
    "gid": "ff0b4e56-ad1b-4d25-8707-042fc099293b"
  },
  {
    "Work": "妖々夢 ～ Snow or Cherry Petal (東方妖々夢)",
    "Writers": "ZUN (composer)",
    "Artists": "TAMUSIC  WAVE  ZUN  Jun.A  鯛の小骨  Diverse System  Azure & Sands  青汁  絃奏水琴樂章  SWING HOLIC  Alstroemeria Records  Factory Noise & AG  Sensitive Heart  Sound Online  AniPix  白いしましまうさぎ  きくちけ  Bizen  Lix  ハム  NAGI☆  Maurits\"禅\"Cornelis  Hizuru  HertzDevil  heric  凛",
    "ISWC": null,
    "Type": null,
    "Lyrics Languages": "zxx",
    "Attributes": null,
    "Rating": null,
    "gid": "ff0b4e56-ad1b-4d25-8707-042fc099293b"
  },
  {
    "Work": "子午線の祀り (Meridian Dance, Secret of Mana)",
    "Writers": "菊田裕樹 (composer)",
    "Artists": "菊田裕樹  Jun Muratani  EXCELSIA  東京フィルハーモニー交響楽団  Jonne Valtonen  Fishy  supply  Lix  (S_S)  Christian Pacaud, MAG & ktriton  ひとおおかみ  Delldongo  Dynastess  RIO  Rebecca Tripp  Ian Martyn  The Travelers  Omigadrive, Prince of Darkness and more",
    "ISWC": null,
    "Type": "Song",
    "Lyrics Languages": "zxx",
    "Attributes": null,
    "Rating": null,
    "gid": "ff0b4e56-ad1b-4d25-8707-042fc099293b"
  },
  {
    "Work": "幻獣を守れ！ (Final Fantasy VI)",
    "Writers": "植松伸夫 (composer)",
    "Artists": "植松伸夫  mp  Lix  Fishy feat. XPRTNovice  Jun Muratani  パポス  Sean Schafianski  ThePopStarDude  Pontus Hultgren",
    "ISWC": null,
    "Type": null,
    "Lyrics Languages": "zxx",
    "Attributes": null,
    "Rating": null,
    "gid": "ff0b4e56-ad1b-4d25-8707-042fc099293b"
  },
  {
    "Work": "悠久の風 (Final Fantasy III)",
    "Writers": "植松伸夫 (composer)",
    "Artists": "植松伸夫  春風の並木道  DE DE MOUSE  Avien  MintJam  石元丈晴  narve  Select Start  Velvet Sounds  Ante  Nobuo Uematsu  Lix  関口祐二  yue  Nobuyuki Hirakura  Delldongo  いわま ひろゆき  preludio  EXCELSIA  Banets!  TAM + A-dash  Mister G & FFmusic Dj  ジェット",
    "ISWC": null,
    "Type": "Soundtrack",
    "Lyrics Languages": "zxx",
    "Attributes": null,
    "Rating": null,
    "gid": "ff0b4e56-ad1b-4d25-8707-042fc099293b"
  },
  {
    "Work": "戦い2 (“Battle 2” from Chrono Trigger)",
    "Writers": "光田康典 (composer)",
    "Artists": "光田康典  RoeTaKa  Lix  The Blake Robinson Synthetic Orchestra  ししあ  Careless Juja",
    "ISWC": null,
    "Type": null,
    "Lyrics Languages": "zxx",
    "Attributes": "034-3652-7 (JASRAC ID)",
    "Rating": null,
    "gid": "ff0b4e56-ad1b-4d25-8707-042fc099293b"
  },
  {
    "Work": "新しき世界 (Final Fantasy V)",
    "Writers": "植松伸夫 (composer)",
    "Artists": "植松伸夫  ARM  Lix  Meteo Xavier  (S_S)  ゆう  春風の並木道  大臣  EXCELSIA  ししあ  TAM×ときまどうし  Rebecca Tripp  RiverSound",
    "ISWC": null,
    "Type": "Song",
    "Lyrics Languages": "zxx",
    "Attributes": null,
    "Rating": null,
    "gid": "ff0b4e56-ad1b-4d25-8707-042fc099293b"
  },
  {
    "Work": "更に闘う者達 (\"Fight On!\"\/\"Those Who Fight Further\"\/\"Still More Fighting\", Final Fantasy VII)",
    "Writers": "植松伸夫 (composer)",
    "Artists": "植松伸夫  The Black Mages  zircon  石元丈晴  CarboHydroM  Hellion Sounds  Standby  Fishy  Armcannon  Piano Squall  The Runaway Five  おのっち  →Pia-no-jaC←  Artificial Fear  Daniel Tidwell  Nobuo Uematsu  Lix  Random Encounter  (S_S)  koro  Knight of the Round  JOYH-TV  Jun Muratani  Triforce Quartet  ししあ  Nightlock  TAM×Hikaru  Zebes System  Audio Sprite  Ferdk  ToxicxEternity  Fisherman's Horizon  MrSolidSnake745's Floppy Drive Orchestra  Jade Arcade  Andersongs87  Siena Wind Orchestra  The Hit Points  Kara Comparetto  Pontus Hultgren  Video Game Music Box",
    "ISWC": null,
    "Type": "Song",
    "Lyrics Languages": "zxx",
    "Attributes": null,
    "Rating": null,
    "gid": "ff0b4e56-ad1b-4d25-8707-042fc099293b"
  },
  {
    "Work": "樹海の神秘 (“Secret of the Forest” from Chrono Trigger)",
    "Writers": "光田康典 (composer)",
    "Artists": "光田康典  Lix  Mustin  mp  Kunal Majmudar  AeroZ  DrumUltimA  Retro Remix Revue  Homeslice  The Blake Robinson Synthetic Orchestra  Argle  Tuned Logic  Kirby's Dream Band  大臣  Rebecca Tripp  Richard Daskas  The Greatest Bits  Malcolm Robinson  Steven Morris & Soundole  Dylan Wiest  Wiesty & The OC Jazz Collective  PokérusVGM  ZiSotto  Xnarky  MAYA  Federico Dubbini  Andrew Thompson, Kristy Mezines & Fernando Valencia  Video Game Music Box",
    "ISWC": null,
    "Type": "Song",
    "Lyrics Languages": "zxx",
    "Attributes": "034-3652-7 (JASRAC ID)",
    "Rating": null,
    "gid": "ff0b4e56-ad1b-4d25-8707-042fc099293b"
  },
  {
    "Work": "決戦 (Final Fantasy V)",
    "Writers": "植松伸夫 (composer)",
    "Artists": "植松伸夫  CROW'SCLAW  Nekofrog  Lix  いわま ひろゆき  Jun Muratani  EXCELSIA  ししあ  あず♪",
    "ISWC": null,
    "Type": null,
    "Lyrics Languages": "zxx",
    "Attributes": null,
    "Rating": null,
    "gid": "ff0b4e56-ad1b-4d25-8707-042fc099293b"
  },
  {
    "Work": "無何有の郷 ～ Deep Mountain (東方妖々夢)",
    "Writers": "ZUN (composer)",
    "Artists": "TAMUSIC  Demetori  CROW'SCLAW  絃奏水琴樂章  石鹸屋  Silver Forest  ZUN  WAVE  IOSYS  Justus Johnston  Azure & Sands  IRON ATTACK!  SWING HOLIC  Scinicade  =NeutraL=  セブンスヘブンMAXION  Sensitive Heart  AniPix  白いしましまうさぎ  Melodic Taste  Lix  すみじゅん  JOYH-TV  HertzDevil  GET IN THE RING  Coro  KA=YA  soundartz  凛",
    "ISWC": null,
    "Type": null,
    "Lyrics Languages": "zxx",
    "Attributes": null,
    "Rating": null,
    "gid": "ff0b4e56-ad1b-4d25-8707-042fc099293b"
  },
  {
    "Work": "竹取飛翔 ～ Lunatic Princess (東方永夜抄)",
    "Writers": "ZUN (composer)",
    "Artists": "TAMUSIC  愛新覚羅溥儀  石鹸屋  ZUN  WAVE  IOSYS  Azure & Sands  Alstroemeria Records  Kraster  Lix  発熱巫女〜ず  凛  UI-70  Jun.A  CROW'SCLAW  C-CLAYS  MyonMyon  絃奏水琴樂章  弘世  SWING HOLIC  Scinicade  Factory Noise & AG  Dark PHOENiX  =NeutraL=  Silver Forest  ALiCE'S EMOTiON  Liz Triangle  かりんとう  EastNewSound  Sensitive Heart  EcN  sun3  UtAGe  Alice Music  k-waves LAB  まらしぃ  Melodic Taste  綾倉盟  Bizen  ハム  NAGI☆  削除  Tutti Sound  馬島昇  RichaadEB  Floating Cloud Acoustic Band  交響アクティブNEETs  REDALiCE feat.野宮あゆみ  Baguettes Ensemble  あるす",
    "ISWC": null,
    "Type": null,
    "Lyrics Languages": "zxx",
    "Attributes": null,
    "Rating": null,
    "gid": "ff0b4e56-ad1b-4d25-8707-042fc099293b"
  },
  {
    "Work": "花映塚 ～ Higan Retour (東方花映塚)",
    "Writers": "ZUN (composer)",
    "Artists": "ZUN  Alstroemeria Records  Halozy  鯛の小骨  SOUND HOLIC  C-CLAYS  MyonMyon  SWING HOLIC  鷹  きくちけ  Alstroemeria Records & Cradle  Lix  heric  凛",
    "ISWC": null,
    "Type": null,
    "Lyrics Languages": "zxx",
    "Attributes": null,
    "Rating": null,
    "gid": "ff0b4e56-ad1b-4d25-8707-042fc099293b"
  },
  {
    "Work": "運命のコイン (Final Fantasy VI)",
    "Writers": "植松伸夫 (composer)",
    "Artists": "植松伸夫  Daniel Brown  Lix  MintJam  Level 99  Matheus Manente  Kenmochi Hidefumi  Some Two Dudes  TheRedMage13  Nobuyuki Hirakura  Rute feat. Mizuki  EXCELSIA  Eiko Nichols  Pontus Hultgren",
    "ISWC": null,
    "Type": null,
    "Lyrics Languages": "zxx",
    "Attributes": null,
    "Rating": null,
    "gid": "ff0b4e56-ad1b-4d25-8707-042fc099293b"
  },
  {
    "Work": "飛空艇ブラックジャック (Final Fantasy VI)",
    "Writers": "植松伸夫 (composer)",
    "Artists": "植松伸夫  Jun Muratani  Radiowar  Eric's Little Shack  Lix  DDRKirby(ISQ)  Calum Bowen feat. Xarnax42  EXCELSIA  Dewey Newt, Kiaran, WyattWMusic & VideoGamesG33k",
    "ISWC": null,
    "Type": null,
    "Lyrics Languages": "zxx",
    "Attributes": null,
    "Rating": null,
    "gid": "ff0b4e56-ad1b-4d25-8707-042fc099293b"
  }
]
